<?xml version="1.0" encoding="windows-1252"?>
<XYDiagram name="Komatiite Classification MgO vs FeO (Barnes et al, 2004)" variateMode="Multi">
   <GeochemAxisX element="MgO" unit="pct" log="false"/>
   <GeochemAxisY element="FeO" unit="pct" log="false"/>
   <Bounds x="-17.106546" y="2.593838" w="95.02448" h="22.108196" />
   <Comment>MgO vs FeO plot used for comparison between compositions of komatiites.</Comment>
   <Comment>The plot shows contours of data density for each komatiite facies type in the study area.</Comment>
   <Comment>LLLS = Layered lava lakes or sills, CSF = Channelised sheet flows, TDF = Thin differentiated flow, DCSF = Dunitic channelised sheet flows</Comment>
   <Comment>Heavy sloping lines represented by the Fo and Ens polygons represent compositions of forsterite and enstatite, respectively</Comment>
   <Comment>Ticks indicate mol% forsterite and enstatite. Light gray sloping straight lines indicates olivines in equilibrium with olivine of forsterite content</Comment>
   <Reference>Barnes, SJ, Hill, RET, Perring, CS &amp; Dowling, SE, 2004. Lithogeochemical exploration for komatiite-associated Ni-sulfide deposits: strategies and limitations. Mineralogy and Petrology, 82, 259-293.</Reference>
   <Poly name="DCSF" visible="true" closed="true" endArrow="false">
      <Colour r="127" g="0" b="255"/>
      <LabelAngle angle="0.0" />
      <LabelPos x="47.961212" y="6.841718" />
      <Boundary3>
         <Linear>
            <BezierPoint x="50.948322" y="4.7356615" sectionEnd="false"/>
         </Linear>
         <Linear>
            <BezierPoint x="53.144726" y="5.3100405" sectionEnd="false"/>
         </Linear>
         <Linear>
            <BezierPoint x="52.52973" y="6.937448" sectionEnd="false"/>
         </Linear>
         <Linear>
            <BezierPoint x="50.77261" y="7.8181624" sectionEnd="false"/>
         </Linear>
         <Linear>
            <BezierPoint x="46.555515" y="8.890337" sectionEnd="false"/>
         </Linear>
         <Linear>
            <BezierPoint x="43.392696" y="8.928629" sectionEnd="false"/>
         </Linear>
         <Linear>
            <BezierPoint x="42.86556" y="8.373396" sectionEnd="false"/>
         </Linear>
         <Linear>
            <BezierPoint x="45.061962" y="7.014032" sectionEnd="false"/>
         </Linear>
         <Linear>
            <BezierPoint x="46.994797" y="6.5928206" sectionEnd="false"/>
         </Linear>
         <Linear>
            <BezierPoint x="49.015488" y="5.3483324" sectionEnd="false"/>
         </Linear>
         <Linear>
            <BezierPoint x="51.03618" y="4.7548075" sectionEnd="false"/>
         </Linear>
      </Boundary3>
   </Poly>
   <Poly name="Olivine" visible="true" closed="true" endArrow="false">
      <Colour r="204" g="255" b="204"/>
      <LabelAngle angle="0.0" />
      <LabelPos x="49.065918" y="9.388132" />
      <Boundary3>
         <Linear>
            <BezierPoint x="38.301693" y="22.247131" sectionEnd="false"/>
         </Linear>
         <Linear>
            <BezierPoint x="52.18466" y="5.0498385" sectionEnd="false"/>
         </Linear>
         <Linear>
            <BezierPoint x="53.241497" y="5.6655984" sectionEnd="false"/>
         </Linear>
         <Linear>
            <BezierPoint x="39.022263" y="22.862892" sectionEnd="false"/>
         </Linear>
      </Boundary3>
   </Poly>
   <Poly name="LLLS" visible="true" closed="true" endArrow="false">
      <Colour r="51" g="255" b="255"/>
      <LabelAngle angle="0.0" />
      <LabelPos x="42.500813" y="9.5413" />
      <Boundary3>
         <Linear>
            <BezierPoint x="51.08595" y="6.018441" sectionEnd="false"/>
         </Linear>
         <Linear>
            <BezierPoint x="50.075935" y="7.626703" sectionEnd="false"/>
         </Linear>
         <Linear>
            <BezierPoint x="48.777344" y="9.656176" sectionEnd="false"/>
         </Linear>
         <Linear>
            <BezierPoint x="47.767326" y="11.494189" sectionEnd="false"/>
         </Linear>
         <Linear>
            <BezierPoint x="42.42867" y="13.083304" sectionEnd="false"/>
         </Linear>
         <Linear>
            <BezierPoint x="37.59502" y="12.432342" sectionEnd="false"/>
         </Linear>
         <Linear>
            <BezierPoint x="34.49283" y="10.192263" sectionEnd="false"/>
         </Linear>
         <Linear>
            <BezierPoint x="33.98782" y="9.043505" sectionEnd="false"/>
         </Linear>
         <Linear>
            <BezierPoint x="41.70723" y="8.54571" sectionEnd="false"/>
         </Linear>
         <Linear>
            <BezierPoint x="47.045887" y="6.363069" sectionEnd="false"/>
         </Linear>
         <Linear>
            <BezierPoint x="50.94166" y="5.9801493" sectionEnd="false"/>
         </Linear>
      </Boundary3>
   </Poly>
   <Poly name="CSF" visible="true" closed="true" endArrow="false">
      <Colour r="255" g="127" b="127"/>
      <LabelAngle angle="0.0" />
      <LabelPos x="37.37859" y="8.890337" />
      <Boundary3>
         <Linear>
            <BezierPoint x="24.320524" y="11.264438" sectionEnd="false"/>
         </Linear>
         <Linear>
            <BezierPoint x="29.659182" y="11.570773" sectionEnd="false"/>
         </Linear>
         <Linear>
            <BezierPoint x="30.74134" y="10.766642" sectionEnd="false"/>
         </Linear>
         <Linear>
            <BezierPoint x="31.318493" y="9.905073" sectionEnd="false"/>
         </Linear>
         <Linear>
            <BezierPoint x="40.98579" y="9.924219" sectionEnd="false"/>
         </Linear>
         <Linear>
            <BezierPoint x="46.108013" y="9.44557" sectionEnd="false"/>
         </Linear>
         <Linear>
            <BezierPoint x="49.89405" y="8.430834" sectionEnd="false"/>
         </Linear>
         <Linear>
            <BezierPoint x="50.86952" y="6.822572" sectionEnd="false"/>
         </Linear>
         <Linear>
            <BezierPoint x="49.42664" y="6.1907554" sectionEnd="false"/>
         </Linear>
         <Linear>
            <BezierPoint x="44.737278" y="6.401361" sectionEnd="false"/>
         </Linear>
         <Linear>
            <BezierPoint x="39.326477" y="7.2629294" sectionEnd="false"/>
         </Linear>
         <Linear>
            <BezierPoint x="36.729294" y="8.124498" sectionEnd="false"/>
         </Linear>
         <Linear>
            <BezierPoint x="32.905663" y="8.44998" sectionEnd="false"/>
         </Linear>
         <Linear>
            <BezierPoint x="27.927725" y="8.698877" sectionEnd="false"/>
         </Linear>
         <Linear>
            <BezierPoint x="23.959805" y="9.771051" sectionEnd="false"/>
         </Linear>
         <Linear>
            <BezierPoint x="24.031948" y="11.245292" sectionEnd="false"/>
         </Linear>
      </Boundary3>
   </Poly>
   <Poly name="TDF" visible="true" closed="true" endArrow="false">
      <Colour r="153" g="153" b="0"/>
      <LabelAngle angle="0.0" />
      <LabelPos x="27.422716" y="10.000803" />
      <Boundary3>
         <Linear>
            <BezierPoint x="12.056044" y="11.149562" sectionEnd="false"/>
         </Linear>
         <Linear>
            <BezierPoint x="14.003932" y="9.7136135" sectionEnd="false"/>
         </Linear>
         <Linear>
            <BezierPoint x="20.713324" y="10.173117" sectionEnd="false"/>
         </Linear>
         <Linear>
            <BezierPoint x="25.33054" y="8.775461" sectionEnd="false"/>
         </Linear>
         <Linear>
            <BezierPoint x="33.55496" y="8.737169" sectionEnd="false"/>
         </Linear>
         <Linear>
            <BezierPoint x="41.92366" y="8.0479145" sectionEnd="false"/>
         </Linear>
         <Linear>
            <BezierPoint x="42.78939" y="8.890337" sectionEnd="false"/>
         </Linear>
         <Linear>
            <BezierPoint x="38.244316" y="10.115679" sectionEnd="false"/>
         </Linear>
         <Linear>
            <BezierPoint x="33.04995" y="11.417605" sectionEnd="false"/>
         </Linear>
         <Linear>
            <BezierPoint x="23.310509" y="11.953692" sectionEnd="false"/>
         </Linear>
      </Boundary3>
   </Poly>
   <Poly name="Opx" visible="true" closed="true" endArrow="false">
      <Colour r="0" g="204" b="204"/>
      <LabelAngle angle="0.0" />
      <LabelPos x="29.030369" y="9.615091" />
      <Boundary3>
         <Linear>
            <BezierPoint x="34.17043" y="6.424242" sectionEnd="false"/>
         </Linear>
         <Linear>
            <BezierPoint x="20.57569" y="15.573905" sectionEnd="false"/>
         </Linear>
         <Linear>
            <BezierPoint x="19.999235" y="15.304797" sectionEnd="false"/>
         </Linear>
         <Linear>
            <BezierPoint x="33.642014" y="6.11669" sectionEnd="false"/>
         </Linear>
         <Linear>
            <BezierPoint x="34.17043" y="6.424242" sectionEnd="false"/>
         </Linear>
      </Boundary3>
   </Poly>
   <PointFeature name="Fo85" visible="true" x="45.4" y="14.2895" pixelRadius="5.0" >
      <Colour r="0" g="204" b="0"/>
      <LabelAngle angle="0.0" />
   </PointFeature>
   <PointFeature name="Fo86" visible="true" x="46.1" y="13.4" pixelRadius="5.0" >
      <Colour r="0" g="204" b="0"/>
      <LabelAngle angle="0.0" />
   </PointFeature>
   <PointFeature name="Fo87" visible="true" x="46.379803" y="12.355758" pixelRadius="5.0" >
      <Colour r="0" g="204" b="0"/>
      <LabelAngle angle="0.0" />
   </PointFeature>
   <PointFeature name="Fo88" visible="true" x="47.6" y="11.1" pixelRadius="5.0" >
      <Colour r="0" g="204" b="0"/>
      <LabelAngle angle="0.0" />
   </PointFeature>
   <PointFeature name="Fo89" visible="true" x="48.04907" y="10.383722" pixelRadius="5.0" >
      <Colour r="0" g="204" b="0"/>
      <LabelAngle angle="0.0" />
   </PointFeature>
   <PointFeature name="Fo90" visible="true" x="49.1" y="9.7" pixelRadius="5.0" >
      <Colour r="0" g="204" b="0"/>
      <LabelAngle angle="0.0" />
   </PointFeature>
   <PointFeature name="Fo91" visible="true" x="49.89405" y="8.430834" pixelRadius="5.0" >
      <Colour r="0" g="204" b="0"/>
      <LabelAngle angle="0.0" />
   </PointFeature>
   <PointFeature name="Fo92" visible="true" x="50.6" y="7.8" pixelRadius="5.0" >
      <Colour r="0" g="204" b="0"/>
      <LabelAngle angle="0.0" />
   </PointFeature>
   <PointFeature name="Fo93" visible="true" x="51.826885" y="6.458799" pixelRadius="5.0" >
      <Colour r="0" g="204" b="0"/>
      <LabelAngle angle="0.0" />
   </PointFeature>
   <PointFeature name="Fo94" visible="true" x="52.2" y="5.9" pixelRadius="5.0" >
      <Colour r="0" g="204" b="0"/>
      <LabelAngle angle="0.0" />
   </PointFeature>
   <PointFeature name="Fo95" visible="true" x="53.584007" y="4.50591" pixelRadius="5.0" >
      <Colour r="0" g="204" b="0"/>
      <LabelAngle angle="0.0" />
   </PointFeature>
   <PointFeature name="En90" visible="true" x="33.593975" y="6.5" pixelRadius="5.0" >
      <Colour r="153" g="154" b="155"/>
      <LabelAngle angle="0.0" />
   </PointFeature>
   <PointFeature name="En88" visible="true" x="31.3" y="7.6" pixelRadius="5.0" >
      <Colour r="196" g="116" b="53"/>
      <LabelAngle angle="0.0" />
   </PointFeature>
   <PointFeature name="En80" visible="true" x="26.0" y="11.6" pixelRadius="5.0" >
      <Colour r="212" g="0" b="0"/>
      <LabelAngle angle="0.0" />
   </PointFeature>
   <PointFeature name="En84" visible="true" x="28.5" y="9.7" pixelRadius="5.0" >
      <Colour r="255" g="222" b="41"/>
      <LabelAngle angle="0.0" />
   </PointFeature>
   <PointFeature name="En76" visible="true" x="23.7" y="13.3" pixelRadius="5.0" >
      <Colour r="50" g="219" b="219"/>
      <LabelAngle angle="0.0" />
   </PointFeature>
   <PointFeature name="En74" visible="true" x="22.6" y="14.1" pixelRadius="5.0" >
      <Colour r="0" g="0" b="204"/>
      <LabelAngle angle="0.0" />
   </PointFeature>
   <Label name="Fo76" visible="true" x="39.1" y="22.0" >
      <Colour r="251" g="167" b="27"/>
      <LabelAngle angle="0.0" />
   </Label>
   <Label name="Fo84" visible="true" x="44.7" y="15.2" >
      <Colour r="87" g="183" b="87"/>
      <LabelAngle angle="0.0" />
   </Label>
   <Label name="Fo78" visible="true" x="40.5" y="20.3" >
      <Colour r="103" g="130" b="192"/>
      <LabelAngle angle="0.0" />
   </Label>
   <Label name="Fo82" visible="true" x="43.2" y="16.9" >
      <Colour r="66" g="88" b="201"/>
      <LabelAngle angle="0.0" />
   </Label>
   <Label name="Fo80" visible="true" x="41.8" y="18.7" >
      <Colour r="154" g="66" b="200"/>
      <LabelAngle angle="0.0" />
   </Label>
   <Line name="82" visible="true" m="1.31" c="0.0" >
      <Colour r="153" g="153" b="153"/>
      <LabelAngle angle="0.0" />
   </Line>
   <Line name="84" visible="true" m="1.15" c="0.0" >
      <Colour r="153" g="153" b="153"/>
      <LabelAngle angle="0.0" />
   </Line>
   <Line name="86" visible="true" m="0.998" c="0.0" >
      <Colour r="153" g="153" b="153"/>
      <LabelAngle angle="0.0" />
   </Line>
   <Line name="88" visible="true" m="0.853" c="0.0" >
      <Colour r="153" g="153" b="153"/>
      <LabelAngle angle="0.0" />
   </Line>
   <Line name="89" visible="true" m="0.715" c="0.0" >
      <Colour r="153" g="153" b="153"/>
      <LabelAngle angle="0.0" />
   </Line>
   <Line name="90" visible="true" m="0.582" c="0.0" >
      <Colour r="153" g="153" b="153"/>
      <LabelAngle angle="0.0" />
   </Line>
   <Line name="91" visible="true" m="0.518" c="0.0" >
      <Colour r="153" g="153" b="153"/>
      <LabelAngle angle="0.0" />
   </Line>
   <Line name="92" visible="true" m="0.456" c="0.0" >
      <Colour r="153" g="153" b="153"/>
      <LabelAngle angle="0.0" />
   </Line>
   <Line name="93" visible="true" m="0.394" c="0.0" >
      <Colour r="153" g="153" b="153"/>
      <LabelAngle angle="0.0" />
   </Line>
   <Line name="94" visible="true" m="0.335" c="0.0" >
      <Colour r="153" g="153" b="153"/>
      <LabelAngle angle="0.0" />
   </Line>
   <Line name="95" visible="true" m="0.276" c="0.0" >
      <Colour r="153" g="153" b="153"/>
      <LabelAngle angle="0.0" />
   </Line>
   <Polygon name="_ v6.1 required to open diagram _" visible="true" >
      <Point x="30" y="30" />
      <Point x="200" y="30" />
      <Point x="200" y="40" />
      <Point x="30" y="40" />
   </Polygon>
</XYDiagram>
